{
  "totalPages": 7,
  "header": {
    "lines": [
      "แผนการจัดการเรียนรู้",
      "กลุ่มสาระการเรียนรู้ คณิตศาสตร์ ชั้นประถมศึกษาปีที่1",
      "หน่วยการเรียนรู้ที่ 2การบวกจำนวนสองจำนวนที่มีผลบวกไม่เกิน10 เวลาเรียน 18 ชั่วโมง"
    ],
    "extra": [
      "แผนการจัดการเรียนรู้ที่9 เรื่องการบวกจำนวนเดียวกัน เวลาเรียน 1 ชั่วโมง",
      "สอนวันที่.................................... เดือน........................................................ พ.ศ........................................."
    ]
  },
  "preTable": [
    {
      "x": 85,
      "text": "มาตรฐานการเรียนรู้/ตัวชี้วัด",
      "heading": true
    },
    {
      "x": 121,
      "text": "มาตรฐานการเรียนรู้",
      "heading": true
    },
    {
      "x": 126,
      "text": "มาตรฐาน ค1.1 เข้าใจความหลากหลายของการแสดงจำนวน ระบบจำนวน การดำเนินการของ",
      "heading": false
    },
    {
      "x": 85,
      "text": "จำนวน ผลที่เกิดขึ้นจากการดำเนินการ สมบัติของการดำเนินการ และนำไปใช้",
      "heading": false
    },
    {
      "x": 121,
      "text": "ตัวชี้วัด",
      "heading": true
    },
    {
      "x": 129,
      "text": "ค1.1ป.1/4 หาค่าของตัวไม่ทราบค่าในประโยคสัญลักษณ์แสดงการบวก และประโยค",
      "heading": false
    },
    {
      "x": 85,
      "text": "สัญลักษณ์แสดงการลบของจำนวนนับไม่เกิน100และ0",
      "heading": false
    },
    {
      "x": 85,
      "text": "สมรรถนะหลัก",
      "heading": true
    },
    {
      "x": 121,
      "text": "- คณิตศาสตร์ในชีวิตประจำวัน",
      "heading": false
    },
    {
      "x": 121,
      "text": "- ภาษาไทยเพื่อการสื่อสาร",
      "heading": false
    },
    {
      "x": 121,
      "text": "- การทำงานแบบรวมพลังเป็นทีมและภาวะผู้นำ",
      "heading": false
    },
    {
      "x": 121,
      "text": "- ทักษะอาชีพและการเป็นผู้ประกอบการ",
      "heading": false
    },
    {
      "x": 85,
      "text": "จุดประสงค์การเรียนรู้สู่ตัวชี้วัด",
      "heading": true
    },
    {
      "x": 122,
      "text": "1.อธิบายเกี่ยวการบวกจำนวนเดียวกันได้(K)",
      "heading": false
    },
    {
      "x": 122,
      "text": "2.เขียนแสดงวิธีการบวกจำนวนเดียวกัน พร้อมหาคำตอบได้ถูกต้อง(P)",
      "heading": false
    },
    {
      "x": 122,
      "text": "3.มีความกระตือรือร้นในการร่วมกิจกรรม(A)",
      "heading": false
    },
    {
      "x": 85,
      "text": "สาระสำคัญ",
      "heading": true
    },
    {
      "x": 123,
      "text": "การนำจำนวนที่มีค่าเท่ากันมาบวกกัน หากตัวตั้งเป็นจำนวนใด ตัวบวกก็จะเป็นจำนวนนั้นด้วย",
      "heading": false
    },
    {
      "x": 85,
      "text": "เรียกว่า การบวกจำนวนเดียวกัน",
      "heading": false
    },
    {
      "x": 85,
      "text": "สาระการเรียนรู้",
      "heading": true
    },
    {
      "x": 121,
      "text": "การบวกจำนวนเดียวกัน",
      "heading": false
    },
    {
      "x": 85,
      "text": "คุณลักษณะอันพึงประสงค์",
      "heading": true
    },
    {
      "x": 121,
      "text": "ใฝ่เรียนรู้ มุ่งมั่นในการทำงาน",
      "heading": false
    },
    {
      "x": 85,
      "text": "ชิ้นงานหรือภาระงาน (หลักฐาน ร่องรอยแสดงความรู้)",
      "heading": true
    },
    {
      "x": 121,
      "text": "ผลงานจากกิจกรรมข้อ5",
      "heading": false
    }
  ],
  "activity": {
    "rows": [
      {
        "act": [
          "1.ครูนำนักเรียนทบทวนบทเรียนเรื่อง ศูนย์กับ",
          "การบวก โดยครูเขียนโจทย์บนกระดาน3ข้อ แล้ว",
          "ให้นักเรียนช่วยกันหาคำตอบ จากนั้นให้นักเรียน",
          "ร่วมกันร้องเพลง กำมือขึ้นแล้วหมุนๆ และร่วมทำ",
          "ท่าทางประกอบ จากนั้นครูถามนักเรียนว่ามือข้าง",
          "ซ้ายมีกี่นิ้ว มือข้างขวามีกี่นิ้ว นักเรียนมีนิ้วมือ",
          "ทั้งหมดกี่นิ้ว และหาคำตอบได้อย่างไร",
          "(10นิ้ว มาจาก5 + 5 = 10)"
        ],
        "time": [
          "10"
        ],
        "comp": [
          "คณิตศาสตร์ในชีวิตประจำวัน",
          "- อธิบายความรู้และหลักการทาง",
          "คณิตศาสตร์ที่เชื่อมโยงกับปัญหาหรือ",
          "สถานการณ์ต่าง ๆได้อย่างมีเหตุผลตามวัย",
          "- ใช้ความคิดทางคณิตศาสตร์ที่เรียนหา",
          "ข้อสรุปที่อธิบายความคิดของตนอย่าง",
          "สมเหตุสมผลตามวัย"
        ]
      },
      {
        "act": [
          "2.ให้นักเรียนหยิบดินสอออกมาวางบนโต๊ะคน",
          "ละ3แท่ง จากนั้นนำสีไม้ มาวางเพิ่มอีก3แท่ง ครู",
          "ตั้งคำถามว่า ดินสอและสีไม้รวมกันได้ทั้งหมดกี่แท่ง",
          "ให้นั กเรียนอาสาสมัคร1คน ออกมาเขียนเป็น",
          "ประโยคสัญลักษณ์ จากนั้นให้นักเรียนช่วยกันบอก",
          "ตัวตั้ง ตัวบวก และผลบวก (3 + 3 = 6)"
        ],
        "time": [
          "10"
        ],
        "comp": [
          "คณิตศาสตร์ในชีวิตประจำวัน",
          "- อธิบายความรู้และหลักการทาง",
          "คณิตศาสตร์ที่เชื่อมโยงกับปัญหาหรือ",
          "สถานการณ์ต่าง ๆได้อย่างมีเหตุผลตามวัย",
          "- ใช้ความคิดทางคณิตศาสตร์ที่เรียนหา",
          "ข้อสรุปที่อธิบายความคิดของตนอย่าง",
          "สมเหตุสมผลตามวัย"
        ]
      },
      {
        "act": [
          "3.จากประโยคสัญลักษณ์ในกิจกรรมที่3ครูตั้ง",
          "คำถามว่า ตัวบวกและตั้งตั้ งเป็นจำนวนเดียวกัน",
          "หรือไม่ (จำนวนเดียวกัน) จากนั้นครูจึงอธิบายว่าการ",
          "นำจำนวนที่เหมือนกันมาบวกกัน เรียกว่า การบวก",
          "จำนวนเดียวกันจากนั้นครูกำหนดสถานการณ์มาให้",
          "อีก2ข้อ และให้นั กเรียนช่วยกันออกมาเขียน",
          "ประโยคสัญลักษณ์บนกระดานและช่วยกั นหา",
          "คำตอบ"
        ],
        "time": [
          "10"
        ],
        "comp": [
          "คณิตศาสตร์ในชีวิตประจำวัน",
          "- อธิบายความรู้และหลักการทาง",
          "คณิตศาสตร์ที่เชื่อมโยงกับปัญหาหรือ",
          "สถานการณ์ต่าง ๆได้อย่างมีเหตุผลตามวัย",
          "- ใช้ความคิดทางคณิตศาสตร์ที่เรียนหา",
          "ข้อสรุปที่อธิบายความคิดของตนอย่าง",
          "สมเหตุสมผลตามวัย"
        ]
      },
      {
        "act": [
          "4.ครูติดบั ตรภาพสิ่ งของต่ างๆบนกระดาน",
          "จากนั้ นให้ นั กเรี ยนแต่ ละคน เขี ยนประโยค",
          "สัญลักษณ์จากบัตรภาพที่กำหนดลงในสมุด พร้อม",
          "ทั้งหาคำตอบจำนวน3ข้อ จากนั้นครูและนักเรียน",
          "ร่วมกันตรวจสอบความถูกต้อง"
        ],
        "time": [
          "10"
        ],
        "comp": [
          "คณิตศาสตร์ในชีวิตประจำวัน",
          "- อธิบายความรู้และหลักการทาง",
          "คณิตศาสตร์ที่เชื่อมโยงกับปัญหาหรือ",
          "สถานการณ์ต่าง ๆได้อย่างมีเหตุผลตามวัย",
          "- ใช้ความคิดทางคณิตศาสตร์ที่เรียนหา",
          "ข้อสรุปที่อธิบายความคิดของตนอย่าง",
          "สมเหตุสมผลตามวัย"
        ]
      },
      {
        "act": [
          "5.ให้นักเรียนจับคู่กัน จากนั้นครูแจกใบกิจกรรม",
          "ฝึกทักษะการบวกจำนวนเดียวกัน ให้นั กเรียน",
          "ช่วยกันเขียนประโยคสัญลักษณ์และหาคำตอบ เมื่อ",
          "เสร็จแล้วให้นักเรียนอาสาสมัคร1คู่ ออกมานำเสนอ",
          "คำตอบหน้าชั้นเรียน โดยครูและเพื่อนๆ ร่วมกัน",
          "ตรวจสอบความถูกต้อง หากข้อใดยังไม่ถูกต้อง ให้",
          "นักเรียนคู่อื่นที่เข้าใจช่วยกันแก้ไข และอธิบายให้",
          "เพื่อนๆฟัง จากนั้นครูจึงสรุปคำตอบให้อีกครั้ง"
        ],
        "time": [
          "10"
        ],
        "comp": [
          "การทำงานแบบรวมพลังเป็นทีมและภาวะ",
          "ผู้นำ",
          "-ร่วมทำงานกลุ่มกับเพื่อน ให้ความ",
          "ร่วมมือในการทำงาน รับผิดชอบต่อบทบาท",
          "และหน้าที่ที่ได้รับมอบหมาย",
          "- รับฟังความคิดเห็นของผู้อื่น สนับสนุน",
          "หรือโต้แย้งความคิดเห็นของผู้อื่นอย่างมี",
          "เหตุผล"
        ]
      },
      {
        "act": [
          "6. ให้นักเรียนและครูร่วมกันสรุปความรู้ ดังนี้",
          "- การนำจำนวนที่มีค่าเท่ากันมาบวกกัน หากตัว",
          "ตั้งเป็นจำนวนใด ตัวบวกก็จะเป็นจำนวนนั้นด้วย",
          "เรียกว่า การบวกจำนวนเดียวกัน",
          "- ทำแบบฝึกหัดในหนังสือเรียนคณิตศาสตร์"
        ],
        "time": [
          "10"
        ],
        "comp": [
          "ภาษาไทยเพื่อการสื่อสาร",
          "- พูด และตอบคำถามได้ตรงความหมาย",
          "ชัดเจนมีเหตุผล ถูกกาลเทศะมีมารยาทและ",
          "ถูกต้อง",
          "คณิตศาสตร์ในชีวิตประจำวัน",
          "- ใช้ความคิดทางคณิตศาสตร์ที่เรียนหา",
          "ข้อสรุปที่อธิบายความคิดของตนอย่าง",
          "สมเหตุสมผลตามวัย",
          "ทักษะอาชีพและการเป็นผู้ประกอบการ",
          "- ทำงานด้วยตนเองอย่างตั้งใจ จดจ่อในงาน",
          "ทำงานอย่างตั้งใจจนงานเสร็จ"
        ]
      }
    ]
  },
  "media": {
    "lines": [
      {
        "x": 124,
        "text": "1.เพลง กำมือขึ้นแล้วหมุน ๆ"
      },
      {
        "x": 124,
        "text": "2.ดินสอ/สีไม้"
      },
      {
        "x": 124,
        "text": "3.บัตรภาพสิ่งของต่าง ๆ"
      },
      {
        "x": 124,
        "text": "4.ใบกิจกรรมเรื่อง การบวกจำนวนเดียวกัน"
      }
    ]
  },
  "assess": {
    "lines": [
      {
        "x": 121,
        "text": "1.วิธีการวัดและประเมินผล"
      },
      {
        "x": 139,
        "text": "1.1สังเกตพฤติกรรมของนักเรียนในการเข้าร่วมกิจกรรม"
      },
      {
        "x": 139,
        "text": "1.2สังเกตพฤติกรรมของนักเรียนในการเข้าร่วมกิจกรรมกลุ่ม"
      },
      {
        "x": 121,
        "text": "2.เครื่องมือ"
      },
      {
        "x": 139,
        "text": "2.1แบบสังเกตพฤติกรรมการเข้าร่วมกิจกรรม"
      },
      {
        "x": 139,
        "text": "2.2แบบสังเกตพฤติกรรมการเข้าร่วมกิจกรรมกลุ่ม"
      },
      {
        "x": 121,
        "text": "3.เกณฑ์การประเมิน"
      },
      {
        "x": 139,
        "text": "3.1การประเมินพฤติกรรมการเข้าร่วมกิจกรรม"
      },
      {
        "x": 157,
        "text": "ผ่านตั้งแต่ 2รายการ ถือว่า ผ่าน"
      },
      {
        "x": 157,
        "text": "ผ่าน 1รายการ ถือว่า ไม่ผ่าน"
      },
      {
        "x": 139,
        "text": "3.2การประเมินพฤติกรรมการเข้าร่วมกิจกรรมกลุ่ม"
      },
      {
        "x": 157,
        "text": "คะแนน 9- 10 ระดับดีมาก"
      },
      {
        "x": 157,
        "text": "คะแนน 7- 8 ระดับดี"
      },
      {
        "x": 157,
        "text": "คะแนน 5- 6 ระดับพอใช้"
      },
      {
        "x": 157,
        "text": "คะแนน 0- 4 ระดับควรปรับปรุง"
      }
    ]
  }
}